wango/__init__.py
wango/__main__.py
wango/cli.py
wango-0.1.0.dist-info/AUTHORS.rst
wango-0.1.0.dist-info/LICENSE
wango-0.1.0.dist-info/METADATA
wango-0.1.0.dist-info/WHEEL
wango-0.1.0.dist-info/entry_points.txt
wango-0.1.0.dist-info/top_level.txt
wango-0.1.0.dist-info/RECORD
